httplus/__init__.py
httplus/client.py
httplus/request.py
httplus/response.py
httplus-0.1.2.dist-info/LICENSE
httplus-0.1.2.dist-info/METADATA
httplus-0.1.2.dist-info/WHEEL
httplus-0.1.2.dist-info/RECORD
