Metadata-Version: 2.1
Name: httplus
Version: 0.1.2
Summary: An HTTP asynchronous client.
License: MIT
Author: Manasses Lima
Author-email: manasseslima@gmail.com
Requires-Python: >=3.10,<4.0
Classifier: License :: OSI Approved :: MIT License
Classifier: Programming Language :: Python :: 3
Classifier: Programming Language :: Python :: 3.10
Classifier: Programming Language :: Python :: 3.11
